{
  "project_info": {
    "project_number": "95444634348",
    "project_id": "etatcivil-d7daa",
    "storage_bucket": "etatcivil-d7daa.firebasestorage.app"
  },
  "client": [
    {
      "client_info": {
        "mobilesdk_app_id": "1:95444634348:android:ffb41341a20a91310cf3c9",
        "android_client_info": {
          "package_name": "com.example.declaration_naissance"
        }
      },
      "oauth_client": [
        {
          "client_id": "95444634348-6lbr67hciqkem3j997b4qr9t3egmtnvd.apps.googleusercontent.com",
          "client_type": 3
        }
      ],
      "api_key": [
        {
          "current_key": "AIzaSyBBrmajP5AwcRnJJNEqh1QaThsPdhb_CYA"
        }
      ],
      "services": {
        "appinvite_service": {
          "other_platform_oauth_client": [
            {
              "client_id": "95444634348-6lbr67hciqkem3j997b4qr9t3egmtnvd.apps.googleusercontent.com",
              "client_type": 3
            },
            {
              "client_id": "95444634348-5iflra4n9j77tu99evgc207jelif5rsp.apps.googleusercontent.com",
              "client_type": 2,
              "ios_info": {
                "bundle_id": "com.example.declarationNaissance"
              }
            }
          ]
        }
      }
    }
  ],
  "configuration_version": "1"
}